mcot/__init__.py
mcot/mde/README.rst
mcot/mde/VERSION
mcot/mde/__init__.py
mcot/mde/xps.py
mcot.mde-0.2.0.dist-info/METADATA
mcot.mde-0.2.0.dist-info/WHEEL
mcot.mde-0.2.0.dist-info/namespace_packages.txt
mcot.mde-0.2.0.dist-info/top_level.txt
mcot.mde-0.2.0.dist-info/RECORD
